j2534/__init__.py
j2534/can_connection.py
j2534/canbus.py
j2534/j2534.py
j2534/j2534_connection.py
j2534/j2534_detect.py
kwp2000/__init__.py
kwp2000/can.py
kwp2000/client.py
kwp2000/constants.py
kwp2000/exceptions.py
kwp2000/frames.py
kwp2000/request.py
kwp2000/response.py
kwp2000/services.py
kwp2000/transport.py
kwp2000_can-0.1.0.dist-info/licenses/LICENSE
tp20/__init__.py
tp20/can_connection.py
tp20/constants.py
tp20/exceptions.py
tp20/frames.py
tp20/timing.py
tp20/transport.py
kwp2000_can-0.1.0.dist-info/METADATA
kwp2000_can-0.1.0.dist-info/WHEEL
kwp2000_can-0.1.0.dist-info/top_level.txt
kwp2000_can-0.1.0.dist-info/RECORD
