Metadata-Version: 2.4
Name: kwp2000-can
Version: 0.1.0
Summary: Python library for KWP2000 (Keyword Protocol 2000) communication over CAN bus using TP20 transport protocol and J2534 interface
Author-email: Elias <elias.kotlyar@gmail.com>
License: MIT
Project-URL: Homepage, https://github.com/yourusername/KWP2000-CAN
Project-URL: Documentation, https://github.com/yourusername/KWP2000-CAN#readme
Project-URL: Repository, https://github.com/yourusername/KWP2000-CAN
Project-URL: Issues, https://github.com/yourusername/KWP2000-CAN/issues
Keywords: kwp2000,automotive,diagnostics,can,tp20,j2534,ecu,obd
Classifier: Development Status :: 3 - Alpha
Classifier: Intended Audience :: Developers
Classifier: License :: OSI Approved :: MIT License
Classifier: Programming Language :: Python :: 3
Classifier: Programming Language :: Python :: 3.7
Classifier: Programming Language :: Python :: 3.8
Classifier: Programming Language :: Python :: 3.9
Classifier: Programming Language :: Python :: 3.10
Classifier: Programming Language :: Python :: 3.11
Classifier: Programming Language :: Python :: 3.12
Classifier: Topic :: Software Development :: Libraries :: Python Modules
Classifier: Topic :: System :: Hardware
Classifier: Topic :: Scientific/Engineering
Requires-Python: >=3.7
License-File: LICENSE
Requires-Dist: python-can>=4.0.0
Dynamic: license-file
